{
  "_fv": 39,
  "_type": "tool",
  "definition": {
    "renderType": 0,
    "texture": "aluminium_hammer",
    "customModelName": "Normal",
    "name": "Alluminiumhammer",
    "specialInfo": [],
    "creativeTab": {
      "value": "CUSTOM:Tungstenemod"
    },
    "toolType": "Pickaxe",
    "harvestLevel": 3,
    "efficiency": 4.0,
    "attackSpeed": 1.0,
    "enchantability": 2,
    "damageVsEntity": 4.0,
    "usageCount": 200,
    "blocksAffected": [],
    "hasGlow": false,
    "repairItems": [],
    "immuneToFire": false,
    "stayInGridWhenCrafting": false,
    "damageOnCrafting": false,
    "onBlockDestroyedWithTool": {
      "name": "TungstenehammerQuandLeBlocEstDetruitAvecLoutil"
    }
  }
}